ipm/__init__.py
ipm/__main__.py
ipm/__version__.py
ipm/common.py
ipm/manage.py
efipm-1.0.0.dist-info/LICENSE
efipm-1.0.0.dist-info/METADATA
efipm-1.0.0.dist-info/WHEEL
efipm-1.0.0.dist-info/top_level.txt
efipm-1.0.0.dist-info/RECORD
