Metadata-Version: 2.1
Name: efipm
Version: 1.0.0
Summary: Open-source IPs Package Manager.
Author: Efabless Corporation
Author-email: Efabless Corporation <contact@efabless.com>
Project-URL: Homepage, https://github.com/efabless/IPM
Project-URL: Issues, https://github.com/efabless/IPM/issues
Classifier: License :: OSI Approved :: Apache Software License
Classifier: Programming Language :: Python :: 3
Classifier: Intended Audience :: Developers
Classifier: Operating System :: POSIX :: Linux
Classifier: Operating System :: MacOS :: MacOS X
Requires-Python: >3.6
License-File: LICENSE
